{
    "results": [
        {
            "business_status": "OPERATIONAL",
            "geometry": {
                "location": {
                    "lat": 33.9417948,
                    "lng": -5.2067682
                },
                "viewport": {
                    "northeast": {
                        "lat": 33.94316242989272,
                        "lng": -5.205411470107278
                    },
                    "southwest": {
                        "lat": 33.94046277010728,
                        "lng": -5.208111129892722
                    }
                }
            },
            "icon": "https://maps.gstatic.com/mapfiles/place_api/icons/v1/png_71/generic_business-71.png",
            "name": "Kayak Cars",
            "photos": [
                {
                    "height": 406,
                    "photo_reference": "ATtYBwJCbrlCOQDLPgknMbegLpZn0Th_ZcnCVY8tIWCWAvNFbwYrvs_hPoRhVveg7CHTeuD0LLcEW3HkUdwdY56pdMcv7_Q0mru-tgDVa76HyBS5i9yxmZ6lNRmcd8pSaujQcGVHA4d3c_tKELPbXwTc63FlbQgGHxWSaAyFIeGYDgO07IsJ",
                    "width": 720
                }
            ],
            "place_id": "ChIJ55PugGMloA0R3inGZw7twWc",
            "rating": 4.7,
            "reference": "ChIJ55PugGMloA0R3inGZw7twWc",
            "scope": "MEANZ TEST",
            "types": [
                "car_rental",
                "point_of_interest",
                "establishment"
            ],
            "user_ratings_total": 61,
            "vicinity": "10 Hay Al Qods, Ain Taoujdate 51100, Morocco ",
            "opening_hours": {
                "open_now": true
            }
        },
        {
            "business_status": "OPERATIONAL",
            "geometry": {
                "location": {
                    "lat": 33.93897630000001,
                    "lng": -5.208967599999999
                },
                "viewport": {
                    "northeast": {
                        "lat": 33.94034552989272,
                        "lng": -5.207616220107278
                    },
                    "southwest": {
                        "lat": 33.93764587010727,
                        "lng": -5.210315879892722
                    }
                }
            },
            "icon": "https://maps.gstatic.com/mapfiles/place_api/icons/v1/png_71/generic_business-71.png",
            "name": "Kayak cars Ain Taoujdate",
            "photos": null,
            "place_id": "ChIJdTkC2OoloA0RH_t6QFIX1Ho",
            "rating": 0.0,
            "reference": "ChIJdTkC2OoloA0RH_t6QFIX1Ho",
            "scope": "MEANZ TEST",
            "types": [
                "car_rental",
                "point_of_interest",
                "establishment"
            ],
            "user_ratings_total": 0,
            "vicinity": "R716, Ain Taoujdate, Morocco ",
            "opening_hours": null
        },
        {
            "business_status": "OPERATIONAL",
            "geometry": {
                "location": {
                    "lat": 33.941739,
                    "lng": -5.208404
                },
                "viewport": {
                    "northeast": {
                        "lat": 33.94306767989273,
                        "lng": -5.207009870107278
                    },
                    "southwest": {
                        "lat": 33.94036802010728,
                        "lng": -5.209709529892722
                    }
                }
            },
            "icon": "https://maps.gstatic.com/mapfiles/place_api/icons/v1/png_71/generic_business-71.png",
            "name": "STE SASA CAR",
            "photos": null,
            "place_id": "ChIJV0n_37wkoA0R1JrlUr18uGk",
            "rating": 5.0,
            "reference": "ChIJV0n_37wkoA0R1JrlUr18uGk",
            "scope": "MEANZ TEST",
            "types": [
                "car_rental",
                "point_of_interest",
                "establishment"
            ],
            "user_ratings_total": 1,
            "vicinity": "Ain Taoujdate, Morocco ",
            "opening_hours": null
        },
        {
            "business_status": "OPERATIONAL",
            "geometry": {
                "location": {
                    "lat": 33.93800100000001,
                    "lng": -5.208989
                },
                "viewport": {
                    "northeast": {
                        "lat": 33.93936512989272,
                        "lng": -5.207637870107277
                    },
                    "southwest": {
                        "lat": 33.93666547010728,
                        "lng": -5.210337529892722
                    }
                }
            },
            "icon": "https://maps.gstatic.com/mapfiles/place_api/icons/v1/png_71/generic_business-71.png",
            "name": "DISCOVERY CAR",
            "photos": [
                {
                    "height": 4160,
                    "photo_reference": "ATtYBwIhxDLSiPJQhhJRfGoJ9RgsY98vKlAruJMhFBZIlg_PKJ4GjKeyhAXBr8J87BkeWpJMgUT-d3vUQRpah1pLTg4BA8Pb7IQmgE-U2CcyBmri4xOnJETS8pplRMxwSA4Q7eBWNupGiO22LW8DuNRXqJ_JxJaOIQAtXgedh1ac28zA8_qz",
                    "width": 3120
                }
            ],
            "place_id": "ChIJbfhtL7wkoA0R72GqeKGbc4s",
            "rating": 4.4,
            "reference": "ChIJbfhtL7wkoA0R72GqeKGbc4s",
            "scope": "MEANZ TEST",
            "types": [
                "car_rental",
                "point_of_interest",
                "establishment"
            ],
            "user_ratings_total": 28,
            "vicinity": "152 Hay PAM, Ain Taoujdate, Morocco ",
            "opening_hours": {
                "open_now": true
            }
        },
        {
            "business_status": "OPERATIONAL",
            "geometry": {
                "location": {
                    "lat": 33.9367516,
                    "lng": -5.2120685
                },
                "viewport": {
                    "northeast": {
                        "lat": 33.93806902989272,
                        "lng": -5.210772520107279
                    },
                    "southwest": {
                        "lat": 33.93536937010728,
                        "lng": -5.213472179892722
                    }
                }
            },
            "icon": "https://maps.gstatic.com/mapfiles/place_api/icons/v1/png_71/generic_business-71.png",
            "name": "ZIZO CAR",
            "photos": [
                {
                    "height": 960,
                    "photo_reference": "ATtYBwI_Hwo6YCT_a7odb6ahTruvhNyUHBHql9i0q1KtsEZgKTtmTFZdpr-ux8x0smaQkVXTLVAaqC7EZ2LcdHYHqFv-9l9y4eYZoqv7QDy3GaOsHD-_uHy6JKX-swCltF_XPrLJ3bXPsEsrvHaLPmhozLC1BpiWxNd5626utttZS4cLah0Q",
                    "width": 1280
                }
            ],
            "place_id": "ChIJIfeDMVMloA0Rr-lAX2obfMo",
            "rating": 5.0,
            "reference": "ChIJIfeDMVMloA0Rr-lAX2obfMo",
            "scope": "MEANZ TEST",
            "types": [
                "car_rental",
                "point_of_interest",
                "establishment"
            ],
            "user_ratings_total": 1,
            "vicinity": "Ain Taoujdate, Morocco ",
            "opening_hours": {
                "open_now": true
            }
        },
        {
            "business_status": "OPERATIONAL",
            "geometry": {
                "location": {
                    "lat": 34.0420616,
                    "lng": -4.998322700000001
                },
                "viewport": {
                    "northeast": {
                        "lat": 34.04349537989272,
                        "lng": -4.997133120107278
                    },
                    "southwest": {
                        "lat": 34.04079572010728,
                        "lng": -4.999832779892722
                    }
                }
            },
            "icon": "https://maps.gstatic.com/mapfiles/place_api/icons/v1/png_71/generic_business-71.png",
            "name": "Abid Cars Fes Location de voiture",
            "photos": [
                {
                    "height": 288,
                    "photo_reference": "ATtYBwK-JWml3KFyHJHE_TGpJ3GuBcJN3qCY88hLaCFrrFhsDwuoppGhNt8aDqWQFEzrDiBUTi4laYYxrxeBOISglQq-WGV2g6xjjopdB1Z5vsVHPVKQax0Yb1isNnH3ku8FzYGy1FdX0nbAXqklnEA6JeeZ926qMJJS40QyI9sbM2tNQhzJ",
                    "width": 1200
                }
            ],
            "place_id": "ChIJnUXgwzeLnw0RJgF2j1ydou8",
            "rating": 4.7,
            "reference": "ChIJnUXgwzeLnw0RJgF2j1ydou8",
            "scope": "MEANZ TEST",
            "types": [
                "car_rental",
                "point_of_interest",
                "establishment"
            ],
            "user_ratings_total": 80,
            "vicinity": "41 Avenue Hassan II, Fès 30000, Morocco ",
            "opening_hours": {
                "open_now": true
            }
        },
        {
            "business_status": "OPERATIONAL",
            "geometry": {
                "location": {
                    "lat": 33.9305978,
                    "lng": -4.9822321
                },
                "viewport": {
                    "northeast": {
                        "lat": 33.93205427989272,
                        "lng": -4.980878320107278
                    },
                    "southwest": {
                        "lat": 33.92935462010728,
                        "lng": -4.983577979892722
                    }
                }
            },
            "icon": "https://maps.gstatic.com/mapfiles/place_api/icons/v1/png_71/generic_business-71.png",
            "name": "AIRFLY CAR FEZ",
            "photos": [
                {
                    "height": 576,
                    "photo_reference": "ATtYBwIn2Wspo4AKHCUE40OeOUJlcWM-SKxQ9ecV_QoKZoZCy1dpfUQ4Nc1fjismdkcP0WnifoMKvo1Sb8qaU8eQXseGuy6EZayT23qfRtBu2GOL5GThatfBkt3iSStv6TGa5Y6LddTQQvFt_YBj1J05F7kgGztGwLqoGUlWaWbrrZ9M_lV9",
                    "width": 1022
                }
            ],
            "place_id": "ChIJ3W7fPcSJnw0Rqb-u2SZNiDw",
            "rating": 4.6,
            "reference": "ChIJ3W7fPcSJnw0Rqb-u2SZNiDw",
            "scope": "MEANZ TEST",
            "types": [
                "car_rental",
                "point_of_interest",
                "establishment"
            ],
            "user_ratings_total": 109,
            "vicinity": "Fes Aéroport, Fès 30000, Morocco ",
            "opening_hours": {
                "open_now": true
            }
        },
        {
            "business_status": "OPERATIONAL",
            "geometry": {
                "location": {
                    "lat": 33.9317487,
                    "lng": -4.985029
                },
                "viewport": {
                    "northeast": {
                        "lat": 33.93289747989272,
                        "lng": -4.983681370107278
                    },
                    "southwest": {
                        "lat": 33.93019782010728,
                        "lng": -4.986381029892722
                    }
                }
            },
            "icon": "https://maps.gstatic.com/mapfiles/place_api/icons/v1/png_71/generic_business-71.png",
            "name": "Cerisa Car rent a car",
            "photos": [
                {
                    "height": 360,
                    "photo_reference": "ATtYBwJjncO6g-nNX1jdnC_ZOswsJLhOEOgHMQxv8TKT8KUc2csy1pVlk87LBz4wM3Ec9FsxZWbcTHKenNHQ-rKyCX9nqls7cpStvQ5vzYO8H_vzD1FqC05bhLtbyQRINQgr1E68l3sRxmOGHLEJCWxjZuqWhXefaL7wuzCsm2jpE5AXAGlm",
                    "width": 480
                }
            ],
            "place_id": "ChIJv2nR-DGJnw0RmqjVp0vNujY",
            "rating": 4.3,
            "reference": "ChIJv2nR-DGJnw0RmqjVp0vNujY",
            "scope": "MEANZ TEST",
            "types": [
                "car_rental",
                "point_of_interest",
                "establishment"
            ],
            "user_ratings_total": 140,
            "vicinity": "aéroport fes sais, Fès 30000, Morocco ",
            "opening_hours": {
                "open_now": true
            }
        },
        {
            "business_status": "OPERATIONAL",
            "geometry": {
                "location": {
                    "lat": 33.9316933,
                    "lng": -4.9826117
                },
                "viewport": {
                    "northeast": {
                        "lat": 33.93286687989272,
                        "lng": -4.981259770107277
                    },
                    "southwest": {
                        "lat": 33.93016722010728,
                        "lng": -4.983959429892721
                    }
                }
            },
            "icon": "https://maps.gstatic.com/mapfiles/place_api/icons/v1/png_71/generic_business-71.png",
            "name": "Hertz [Fès Airport]",
            "photos": [
                {
                    "height": 900,
                    "photo_reference": "ATtYBwLSnC6vaIsMHPjxGVRQTcfEcX3EZ0684c3DWoWCJgMoRZPD0GYSBHJtU3fl3RM8yx5CuPWlAOMRs0vudXtaLDs0jkLbzEG36zqNA5x2c_mToxU5b3B_DeGh2WZ07Sor_aGXWbZH2aaS9cCss2XSAivbdWrVI5Qk2dX8zv3UiMJ76OqT",
                    "width": 1600
                }
            ],
            "place_id": "ChIJOyfyji2Jnw0R2FDKDcV8vA0",
            "rating": 2.3,
            "reference": "ChIJOyfyji2Jnw0R2FDKDcV8vA0",
            "scope": "MEANZ TEST",
            "types": [
                "car_rental",
                "point_of_interest",
                "establishment"
            ],
            "user_ratings_total": 103,
            "vicinity": "Aéroport Fès Saiss, Fès 30000, Morocco ",
            "opening_hours": {
                "open_now": true
            }
        },
        {
            "business_status": "OPERATIONAL",
            "geometry": {
                "location": {
                    "lat": 33.931775,
                    "lng": -4.9835761
                },
                "viewport": {
                    "northeast": {
                        "lat": 33.93290647989272,
                        "lng": -4.982232070107278
                    },
                    "southwest": {
                        "lat": 33.93020682010728,
                        "lng": -4.984931729892723
                    }
                }
            },
            "icon": "https://maps.gstatic.com/mapfiles/place_api/icons/v1/png_71/generic_business-71.png",
            "name": "Surprice Car Rentals Fes",
            "photos": null,
            "place_id": "ChIJoTgJbdiJnw0RlwofIh1tZOg",
            "rating": 5.0,
            "reference": "ChIJoTgJbdiJnw0RlwofIh1tZOg",
            "scope": "MEANZ TEST",
            "types": [
                "car_rental",
                "point_of_interest",
                "establishment"
            ],
            "user_ratings_total": 2,
            "vicinity": "2 etage, Oulad tayeb oulia route principal Immouzzer, Fes 30023, Morocco ",
            "opening_hours": {
                "open_now": true
            }
        },
        {
            "business_status": "OPERATIONAL",
            "geometry": {
                "location": {
                    "lat": 33.8968259,
                    "lng": -5.5474739
                },
                "viewport": {
                    "northeast": {
                        "lat": 33.89820572989272,
                        "lng": -5.546112570107279
                    },
                    "southwest": {
                        "lat": 33.89550607010727,
                        "lng": -5.548812229892722
                    }
                }
            },
            "icon": "https://maps.gstatic.com/mapfiles/place_api/icons/v1/png_71/generic_business-71.png",
            "name": "Fayna location",
            "photos": [
                {
                    "height": 313,
                    "photo_reference": "ATtYBwL7Ihqlu_ZZPjln5j8scjojvnKdlTqPgFE27NahRUlUJOaavD0zUPjLfy8euKIf-KMYFI900Wo1dZ_Xo8fXw1iRjkA_372kSAqV2B_dY9pimNOwMvuPtNkBcmmS1AssJOC1G-E2HTcLjHSu9U17Qrsg-CRwirjW52xUNxObn4tusHzB",
                    "width": 557
                }
            ],
            "place_id": "ChIJz5fQSPtFoA0R9h4SSu5N2UY",
            "rating": 4.4,
            "reference": "ChIJz5fQSPtFoA0R9h4SSu5N2UY",
            "scope": "MEANZ TEST",
            "types": [
                "car_rental",
                "point_of_interest",
                "establishment"
            ],
            "user_ratings_total": 5,
            "vicinity": "Av Idriss II Imm15 Appt N 4, Meknès, Morocco ",
            "opening_hours": {
                "open_now": true
            }
        },
        {
            "business_status": "OPERATIONAL",
            "geometry": {
                "location": {
                    "lat": 34.034115,
                    "lng": -5.013348
                },
                "viewport": {
                    "northeast": {
                        "lat": 34.03529827989272,
                        "lng": -5.012219820107277
                    },
                    "southwest": {
                        "lat": 34.03259862010728,
                        "lng": -5.014919479892721
                    }
                }
            },
            "icon": "https://maps.gstatic.com/mapfiles/place_api/icons/v1/png_71/generic_business-71.png",
            "name": "Thrifty Car Rental",
            "photos": [
                {
                    "height": 720,
                    "photo_reference": "ATtYBwJxdla5SMiWArU7LRGyuN5JKAuHQvpjWSnt9wrx1XrHK1FRLwG12GS1PLU9P6nRnA4cmEjSayxoyoE4GAQchltn9az8v3X33XG8kr7RBCE2k3qMcPt8TyMcsDMopO7XEv-ljSafaWbFQv-XohTsx2vFamx2LQTbL37nLd0RWZWuPJ0O",
                    "width": 720
                }
            ],
            "place_id": "ChIJwwlXCxqLnw0RI9wyMfpVZe4",
            "rating": 0.0,
            "reference": "ChIJwwlXCxqLnw0RI9wyMfpVZe4",
            "scope": "MEANZ TEST",
            "types": [
                "car_rental",
                "point_of_interest",
                "establishment"
            ],
            "user_ratings_total": 0,
            "vicinity": "NO 1 KISSARIAT DE LA FOIRE, Fes, Morocco ",
            "opening_hours": {
                "open_now": true
            }
        },
        {
            "business_status": "OPERATIONAL",
            "geometry": {
                "location": {
                    "lat": 34.04251,
                    "lng": -5.001774
                },
                "viewport": {
                    "northeast": {
                        "lat": 34.04387707989272,
                        "lng": -5.000410370107279
                    },
                    "southwest": {
                        "lat": 34.04117742010728,
                        "lng": -5.003110029892722
                    }
                }
            },
            "icon": "https://maps.gstatic.com/mapfiles/place_api/icons/v1/png_71/generic_business-71.png",
            "name": "Hertz Car Rental",
            "photos": [
                {
                    "height": 720,
                    "photo_reference": "ATtYBwJnIStqql_xeCHIquxmDKqhsuDjgBxxsvQpR8uVzu85VCZhTcmXxS663TejjAzQ0DiETBmTOg5XrObcQb-mYCewry_RCK7yawcazSWv2BW5bGtcmlHJq-pxCC1Dtetpx3xJPUnTbPaP72ZGF4PEZ9XVuUN1zEm9Z-VITM6i6PcPFEdD",
                    "width": 720
                }
            ],
            "place_id": "ChIJY_AJOzeLnw0RMfO5TYcrnuA",
            "rating": 2.5,
            "reference": "ChIJY_AJOzeLnw0RMfO5TYcrnuA",
            "scope": "MEANZ TEST",
            "types": [
                "car_rental",
                "point_of_interest",
                "establishment"
            ],
            "user_ratings_total": 17,
            "vicinity": "Kissariat de la Foire, Ave Lalla Meryem, Fès 30050, Morocco ",
            "opening_hours": {
                "open_now": true
            }
        },
        {
            "business_status": "OPERATIONAL",
            "geometry": {
                "location": {
                    "lat": 34.0406383,
                    "lng": -4.9967231
                },
                "viewport": {
                    "northeast": {
                        "lat": 34.04199247989273,
                        "lng": -4.995312770107278
                    },
                    "southwest": {
                        "lat": 34.03929282010728,
                        "lng": -4.998012429892722
                    }
                }
            },
            "icon": "https://maps.gstatic.com/mapfiles/place_api/icons/v1/png_71/generic_business-71.png",
            "name": "AVIS - Location de Voiture Fès Centre Ville",
            "photos": [
                {
                    "height": 628,
                    "photo_reference": "ATtYBwIJpZ920gOd0XzUWsHiXEgk0DZAz9eQMrDG0QXedO7wOc3XhdvwdXSmsgoBRQN71HQ5sE3mWXiB9KF0568TnaxZhtug_nBWdYIuO-_32NAeYkJyk_c15jQBRQA8q67pqSVtMRVJ4ix7bVsYO1HFg5dzk0JMvZRXA4jOpNVcbI_jHZW8",
                    "width": 628
                }
            ],
            "place_id": "ChIJ_cQN4keLnw0R13JnIHCQV-4",
            "rating": 4.6,
            "reference": "ChIJ_cQN4keLnw0R13JnIHCQV-4",
            "scope": "MEANZ TEST",
            "types": [
                "car_rental",
                "point_of_interest",
                "establishment"
            ],
            "user_ratings_total": 208,
            "vicinity": "50 Boulevard Chefchaouni, Fès 30050, Morocco ",
            "opening_hours": {
                "open_now": true
            }
        },
        {
            "business_status": "OPERATIONAL",
            "geometry": {
                "location": {
                    "lat": 34.012888,
                    "lng": -4.974728
                },
                "viewport": {
                    "northeast": {
                        "lat": 34.01425387989272,
                        "lng": -4.973364070107278
                    },
                    "southwest": {
                        "lat": 34.01155422010727,
                        "lng": -4.976063729892722
                    }
                }
            },
            "icon": "https://maps.gstatic.com/mapfiles/place_api/icons/v1/png_71/generic_business-71.png",
            "name": "BARCELO S CAR",
            "photos": [
                {
                    "height": 3024,
                    "photo_reference": "ATtYBwKdDSMScxJdH3UKrRQaaDkfyndFsSQZpymzjJQawaiYDgsl19TwFKPS8Ltkpqy8U3-p-qV7YILK5hl-Uso3hgk0gcgTCRe3BvUlmM83IpBkj8WwyB10pdvFRqZkKVv72opEgGSmAVYuDEUdccaJux-1M7JOkJ7Vz0mMqvm8Yn9aoi6I",
                    "width": 4032
                }
            ],
            "place_id": "ChIJLwzMkIGMnw0Ra9KODXX7bj4",
            "rating": 5.0,
            "reference": "ChIJLwzMkIGMnw0Ra9KODXX7bj4",
            "scope": "MEANZ TEST",
            "types": [
                "car_rental",
                "point_of_interest",
                "establishment"
            ],
            "user_ratings_total": 5,
            "vicinity": "Avenue La Marche Verte, Fès, Maroc، Fes, Morocco ",
            "opening_hours": {
                "open_now": true
            }
        },
        {
            "business_status": "OPERATIONAL",
            "geometry": {
                "location": {
                    "lat": 34.0473734,
                    "lng": -5.0052989
                },
                "viewport": {
                    "northeast": {
                        "lat": 34.04877702989272,
                        "lng": -5.003769020107278
                    },
                    "southwest": {
                        "lat": 34.04607737010728,
                        "lng": -5.006468679892722
                    }
                }
            },
            "icon": "https://maps.gstatic.com/mapfiles/place_api/icons/v1/png_71/generic_business-71.png",
            "name": "Hertz [Fez Railway]",
            "photos": null,
            "place_id": "ChIJiQ2GhY2Lnw0R5J-zUby9VIo",
            "rating": 0.0,
            "reference": "ChIJiQ2GhY2Lnw0R5J-zUby9VIo",
            "scope": "MEANZ TEST",
            "types": [
                "car_rental",
                "point_of_interest",
                "establishment"
            ],
            "user_ratings_total": 0,
            "vicinity": "Ave des Almohades, Fes 30050, Morocco ",
            "opening_hours": {
                "open_now": true
            }
        },
        {
            "business_status": "OPERATIONAL",
            "geometry": {
                "location": {
                    "lat": 34.036827,
                    "lng": -4.9976181
                },
                "viewport": {
                    "northeast": {
                        "lat": 34.03817312989273,
                        "lng": -4.996319970107277
                    },
                    "southwest": {
                        "lat": 34.03547347010728,
                        "lng": -4.999019629892721
                    }
                }
            },
            "icon": "https://maps.gstatic.com/mapfiles/place_api/icons/v1/png_71/generic_business-71.png",
            "name": "Rami Rent Car",
            "photos": [
                {
                    "height": 306,
                    "photo_reference": "ATtYBwJrsaGOamGS3-RoVxmiVRx_BySGERnLSR76XEPpcZaK8LCeYYOwQtZTqz2p1IDXx0Vx2cjqoHyECy4kJg1Scw5r9mSj2CKArJ2jxSjrH7hcoqF9PcW6SqHV1ILfrqRFQ9-OYHooNKuWk8vuIUhV12Ocixnwt4wzVVt1oNyzA0TVIeYg",
                    "width": 460
                }
            ],
            "place_id": "ChIJoXvJpUCLnw0Rg2dc3muOLfg",
            "rating": 4.2,
            "reference": "ChIJoXvJpUCLnw0Rg2dc3muOLfg",
            "scope": "MEANZ TEST",
            "types": [
                "car_rental",
                "point_of_interest",
                "establishment"
            ],
            "user_ratings_total": 27,
            "vicinity": "Fes 30050, Morocco ",
            "opening_hours": {
                "open_now": true
            }
        },
        {
            "business_status": "OPERATIONAL",
            "geometry": {
                "location": {
                    "lat": 34.0165017,
                    "lng": -4.9845369
                },
                "viewport": {
                    "northeast": {
                        "lat": 34.01785457989272,
                        "lng": -4.983181070107277
                    },
                    "southwest": {
                        "lat": 34.01515492010728,
                        "lng": -4.985880729892721
                    }
                }
            },
            "icon": "https://maps.gstatic.com/mapfiles/place_api/icons/v1/png_71/generic_business-71.png",
            "name": "Wego Rentin",
            "photos": null,
            "place_id": "ChIJ2VvntdeLnw0R8K76eGDiELQ",
            "rating": 0.0,
            "reference": "ChIJ2VvntdeLnw0R8K76eGDiELQ",
            "scope": "MEANZ TEST",
            "types": [
                "car_rental",
                "point_of_interest",
                "establishment"
            ],
            "user_ratings_total": 0,
            "vicinity": "144 Avenvue OUAFAE, Route de Sefrou, Fès 30000, Morocco ",
            "opening_hours": {
                "open_now": true
            }
        },
        {
            "business_status": "OPERATIONAL",
            "geometry": {
                "location": {
                    "lat": 34.025382,
                    "lng": -5.013133
                },
                "viewport": {
                    "northeast": {
                        "lat": 34.02673997989272,
                        "lng": -5.011831920107278
                    },
                    "southwest": {
                        "lat": 34.02404032010728,
                        "lng": -5.014531579892722
                    }
                }
            },
            "icon": "https://maps.gstatic.com/mapfiles/place_api/icons/v1/png_71/generic_business-71.png",
            "name": "LAATABICAR",
            "photos": [
                {
                    "height": 3472,
                    "photo_reference": "ATtYBwLmc7cKMf2AyE65FoMM9n_NhKXAPTlyF_WxXLQqg5Ht2EKg294dKRSlIxlIVjEhe2ywy8l089oRmn88XK2gzI1h360IZlQruRfYdVwkGlLwyOmBbNy2YjbO7LhVzz8zI6r29eNmkFaOgj2pzKk1pcFtW9TsLbQhf_-jmdpZXvNpkRub",
                    "width": 4624
                }
            ],
            "place_id": "ChIJT8cfzR6Lnw0RdHq9ZtTcoDo",
            "rating": 5.0,
            "reference": "ChIJT8cfzR6Lnw0RdHq9ZtTcoDo",
            "scope": "MEANZ TEST",
            "types": [
                "car_rental",
                "point_of_interest",
                "establishment"
            ],
            "user_ratings_total": 1,
            "vicinity": "158 LOTS BENNIS HAY RAHA، 30000, Morocco ",
            "opening_hours": {
                "open_now": true
            }
        },
        {
            "business_status": "OPERATIONAL",
            "geometry": {
                "location": {
                    "lat": 34.0382616,
                    "lng": -5.014391199999999
                },
                "viewport": {
                    "northeast": {
                        "lat": 34.03958972989271,
                        "lng": -5.013042120107278
                    },
                    "southwest": {
                        "lat": 34.03689007010727,
                        "lng": -5.015741779892722
                    }
                }
            },
            "icon": "https://maps.gstatic.com/mapfiles/place_api/icons/v1/png_71/generic_business-71.png",
            "name": "Location de voiture fes inova",
            "photos": [
                {
                    "height": 540,
                    "photo_reference": "ATtYBwKcUTaUGcFyXfzE_2UlbgVBZ-Olxw8AmR6o8NxWv74XjJNM69n3xOttAcY0uN253CQQORkSg09E2yJMbrmYRqrG-I3hw7_beFVyysER20pAypDao6_2Yk8VNocZign4in4CL0U3QrVdznkVNSNkcw8muPZ7FodQZvxgCoWw7oPAilEc",
                    "width": 720
                }
            ],
            "place_id": "ChIJr8pP71OLnw0Rpw54vj3GtO0",
            "rating": 5.0,
            "reference": "ChIJr8pP71OLnw0Rpw54vj3GtO0",
            "scope": "MEANZ TEST",
            "types": [
                "car_rental",
                "point_of_interest",
                "establishment"
            ],
            "user_ratings_total": 6,
            "vicinity": "Champs de course bel air 3 résidence zineb etage, Fes 30000, Morocco ",
            "opening_hours": {
                "open_now": true
            }
        }
    ]
}